mooncrawl/__init__.py
mooncrawl/actions.py
mooncrawl/api.py
mooncrawl/blockchain.py
mooncrawl/crawler.py
mooncrawl/data.py
mooncrawl/db.py
mooncrawl/esd.py
mooncrawl/etherscan.py
mooncrawl/identity.py
mooncrawl/middleware.py
mooncrawl/publish.py
mooncrawl/reporter.py
mooncrawl/settings.py
mooncrawl/test_cli.py
mooncrawl/version.py
mooncrawl/contract/__init__.py
mooncrawl/contract/cli.py
mooncrawl/contract/deployment_crawler.py
mooncrawl/contract/test_deployment_crawler.py
mooncrawl/generic_crawler/__init__.py
mooncrawl/generic_crawler/base.py
mooncrawl/generic_crawler/cli.py
mooncrawl/leaderboards_generator/__init__.py
mooncrawl/leaderboards_generator/cli.py
mooncrawl/leaderboards_generator/utils.py
mooncrawl/metadata_crawler/__init__.py
mooncrawl/metadata_crawler/cli.py
mooncrawl/metadata_crawler/db.py
mooncrawl/moonworm_crawler/__init__.py
mooncrawl/moonworm_crawler/cli.py
mooncrawl/moonworm_crawler/continuous_crawler.py
mooncrawl/moonworm_crawler/crawler.py
mooncrawl/moonworm_crawler/db.py
mooncrawl/moonworm_crawler/event_crawler.py
mooncrawl/moonworm_crawler/function_call_crawler.py
mooncrawl/moonworm_crawler/historical_crawler.py
mooncrawl/reports_crawler/__init__.py
mooncrawl/reports_crawler/cli.py
mooncrawl/reports_crawler/queries.py
mooncrawl/state_crawler/Multicall2_interface.py
mooncrawl/state_crawler/__init__.py
mooncrawl/state_crawler/cli.py
mooncrawl/state_crawler/db.py
mooncrawl/state_crawler/web3_util.py
mooncrawl/stats_worker/__init__.py
mooncrawl/stats_worker/dashboard.py
mooncrawl/stats_worker/queries.py
mooncrawl/stats_worker/test_queries.py
mooncrawl-0.5.1.dist-info/METADATA
mooncrawl-0.5.1.dist-info/WHEEL
mooncrawl-0.5.1.dist-info/entry_points.txt
mooncrawl-0.5.1.dist-info/top_level.txt
mooncrawl-0.5.1.dist-info/RECORD
