Metadata-Version: 2.1
Name: mooncrawl
Version: 0.5.1
Summary: Moonstream crawlers
Home-page: https://github.com/bugout-dev/moonstream
Author: Bugout.dev
Author-email: engineers@bugout.dev
License: Apache License 2.0
Platform: all
Classifier: Development Status :: 2 - Pre-Alpha
Classifier: Intended Audience :: Developers
Classifier: Natural Language :: English
Classifier: Programming Language :: Python
Classifier: Programming Language :: Python :: 3
Classifier: Programming Language :: Python :: 3.8
Classifier: Programming Language :: Python :: Implementation :: CPython
Classifier: Topic :: Software Development :: Libraries
Classifier: Topic :: Software Development :: Libraries :: Python Modules
Requires-Python: >=3.6
Requires-Dist: boto3
Requires-Dist: bugout >=0.2.13
Requires-Dist: chardet
Requires-Dist: fastapi
Requires-Dist: moonstreamdb >=0.4.6
Requires-Dist: moonstreamdb-v3 >=0.1.3
Requires-Dist: moonstream-types >=0.0.10
Requires-Dist: moonstream >=0.1.2
Requires-Dist: moonworm[moonstream] >=0.9.3
Requires-Dist: humbug
Requires-Dist: pydantic ==1.9.2
Requires-Dist: python-dateutil
Requires-Dist: requests
Requires-Dist: tqdm
Requires-Dist: uvicorn
Requires-Dist: web3 ==5.27.0
Provides-Extra: dev
Requires-Dist: black ; extra == 'dev'
Requires-Dist: isort ; extra == 'dev'
Requires-Dist: mypy ; extra == 'dev'
Requires-Dist: types-requests ; extra == 'dev'
Requires-Dist: types-python-dateutil ; extra == 'dev'
Provides-Extra: distribute
Requires-Dist: build ; extra == 'distribute'
Requires-Dist: twine ; extra == 'distribute'
